slowtorch/__init__.py
slowtorch/_random.py
slowtorch/_tensor.py
slowtorch/_types.py
slowtorch/_utils.py
slowtorch/_variable_functions.py
slowtorch/nn/__init__.py
slowtorch/nn/functional.py
slowtorch/nn/modules.py
slowtorch/optim/__init__.py
slowtorch/optim/optimiser.py
slowtorch-31.5.2025.dist-info/licenses/LICENSE
slowtorch-31.5.2025.dist-info/METADATA
slowtorch-31.5.2025.dist-info/WHEEL
slowtorch-31.5.2025.dist-info/top_level.txt
slowtorch-31.5.2025.dist-info/RECORD
