Metadata-Version: 2.4
Name: slowtorch
Version: 31.5.2025
Summary: Yet another implementation of PyTorch from the ground up, but for real!
Author-email: Akshay Mestry <xa@mes3.dev>
License: MIT License
Project-URL: Code, https://github.com/xames3/slowtorch
Project-URL: Download, https://pypi.org/project/slowtorch/
Project-URL: Homepage, https://github.com/xames3/slowtorch/
Project-URL: Issue tracker, https://github.com/xames3/slowtorch/issues
Keywords: python,pytorch
Classifier: Development Status :: 5 - Production/Stable
Classifier: Intended Audience :: Developers
Classifier: License :: OSI Approved :: MIT License
Classifier: Operating System :: OS Independent
Classifier: Programming Language :: Python
Classifier: Programming Language :: Python :: 3.10
Classifier: Programming Language :: Python :: 3.11
Classifier: Programming Language :: Python :: 3.12
Classifier: Programming Language :: Python :: 3.13
Requires-Python: >=3.10
License-File: LICENSE
Dynamic: license-file
